docker_manager/__init__.py
docker_manager/exceptions.py
docker_manager/bin/__init__.py
docker_manager/bin/console.py
docker_manager/config/__init__.py
docker_manager/docker/__init__.py
docker_manager/docker/compose.py
docker_manager/docker/container.py
docker_manager/docker/project.py
docker_manager/docker/projects.py
docker_manager/docker/sync.py
docker_manager/interface/__init__.py
docker_manager/interface/cli/__init__.py
docker_manager/interface/cli/abstract.py
docker_manager/interface/cli/changedirectory.py
docker_manager/interface/cli/deinit.py
docker_manager/interface/cli/destroy.py
docker_manager/interface/cli/extracommand.py
docker_manager/interface/cli/init.py
docker_manager/interface/cli/projects.py
docker_manager/interface/cli/pull.py
docker_manager/interface/cli/restart.py
docker_manager/interface/cli/start.py
docker_manager/interface/cli/status.py
docker_manager/interface/cli/stop.py
docker_manager/interface/cli/update.py
docker_manager/plugins/__init__.py
docker_manager/plugins/basicauth.py
docker_manager/plugins/hosts.py
docker_manager/plugins/nginx.py
docker_manager-0.0.6.dist-info/DESCRIPTION.rst
docker_manager-0.0.6.dist-info/METADATA
docker_manager-0.0.6.dist-info/RECORD
docker_manager-0.0.6.dist-info/WHEEL
docker_manager-0.0.6.dist-info/entry_points.txt
docker_manager-0.0.6.dist-info/metadata.json
docker_manager-0.0.6.dist-info/top_level.txt
